realhouse/__init__.py
realhouse/_version.py
realhouse/connection/__init__.py
realhouse/core/__init__.py
realhouse/sql/__init__.py
realhouse/utils/__init__.py
realhouse-0.1.0a1.dist-info/licenses/LICENSE
realhouse-0.1.0a1.dist-info/METADATA
realhouse-0.1.0a1.dist-info/WHEEL
realhouse-0.1.0a1.dist-info/top_level.txt
realhouse-0.1.0a1.dist-info/RECORD
